setup.py
nightwatch/__init__.py
nightwatch/nightwatch.py
nightwatch.egg-info/PKG-INFO
nightwatch.egg-info/SOURCES.txt
nightwatch.egg-info/dependency_links.txt
nightwatch.egg-info/requires.txt
nightwatch.egg-info/top_level.txt