Metadata-Version: 2.1
Name: nightwatch
Version: 1.0.7
Summary: Logging
Home-page: UNKNOWN
Author: Pradeep
Author-email: pradeep@incaendo.com
License: MIT
Platform: UNKNOWN
